[{"data":{"id":"Publish-Chocolatey-Packages","source":null,"target":null}},{"data":{"id":"ebd9d322-c8bf-4d78-a058-68b91a3aa48b","source":"Publish-Chocolatey-Packages","target":"Package"}},{"data":{"id":"Package","source":null,"target":null}},{"data":{"id":"4fe40f23-c440-4b08-9995-7bfa205d0102","source":"Package","target":"Export-Release-Notes"}},{"data":{"id":"228d8027-6903-4668-bb70-78eac9653be9","source":"Package","target":"Analyze"}},{"data":{"id":"67a168e4-b27b-4617-a1e2-a2fc089fd16d","source":"Package","target":"Test"}},{"data":{"id":"caddc2d9-11a3-43d6-84f1-74558c7f4f71","source":"Package","target":"Create-NuGet-Packages"}},{"data":{"id":"3be42525-f713-45e1-9bec-27e23560b7b4","source":"Package","target":"Create-Chocolatey-Packages"}},{"data":{"id":"7caaad61-59c7-4be2-98f0-0914bd9dc284","source":"Package","target":"DotNetCore-Pack"}},{"data":{"id":"DotNetCore-Pack","source":null,"target":null}},{"data":{"id":"ef69eecf-ff0c-4904-8597-b5554b2caa97","source":"DotNetCore-Pack","target":"DotNetCore-Build"}},{"data":{"id":"DotNetCore-Build","source":null,"target":null}},{"data":{"id":"5eb137f2-1340-4eed-9ad3-8e89742f21f8","source":"DotNetCore-Build","target":"Clean"}},{"data":{"id":"f441cb7b-6e0e-4706-9598-4a0892378814","source":"DotNetCore-Build","target":"DotNetCore-Restore"}},{"data":{"id":"DotNetCore-Restore","source":null,"target":null}},{"data":{"id":"Clean","source":null,"target":null}},{"data":{"id":"ec622689-1334-43e2-b6a1-a26caa436442","source":"Clean","target":"Show-Info"}},{"data":{"id":"d424e24f-0b2c-4457-a2be-9672fa10b54a","source":"Clean","target":"Print-AppVeyor-Environment-Variables"}},{"data":{"id":"Print-AppVeyor-Environment-Variables","source":null,"target":null}},{"data":{"id":"Show-Info","source":null,"target":null}},{"data":{"id":"Create-Chocolatey-Packages","source":null,"target":null}},{"data":{"id":"be527ac2-857c-4142-8b31-001c16783cf0","source":"Create-Chocolatey-Packages","target":"Clean"}},{"data":{"id":"f2f98e94-6abc-4f68-9516-75f48456974e","source":"Create-Chocolatey-Packages","target":"DotNetCore-Build"}},{"data":{"id":"DotNetCore-Build","source":null,"target":null}},{"data":{"id":"73818331-8746-49f8-a25f-4f7d1c3abbc5","source":"DotNetCore-Build","target":"Clean"}},{"data":{"id":"b9340875-aed7-46e0-ac51-62cdbb28de07","source":"DotNetCore-Build","target":"DotNetCore-Restore"}},{"data":{"id":"DotNetCore-Restore","source":null,"target":null}},{"data":{"id":"Clean","source":null,"target":null}},{"data":{"id":"dbb9958e-03cd-4bf5-904f-84fab1daa676","source":"Clean","target":"Show-Info"}},{"data":{"id":"5e9a34df-7bd3-438c-9a30-4c0c925e5545","source":"Clean","target":"Print-AppVeyor-Environment-Variables"}},{"data":{"id":"Print-AppVeyor-Environment-Variables","source":null,"target":null}},{"data":{"id":"Show-Info","source":null,"target":null}},{"data":{"id":"Clean","source":null,"target":null}},{"data":{"id":"680c6cb2-494c-45e2-b522-a74fd1b5b25f","source":"Clean","target":"Show-Info"}},{"data":{"id":"b837f59a-5f8c-40a9-b265-2b5cb81e931c","source":"Clean","target":"Print-AppVeyor-Environment-Variables"}},{"data":{"id":"Print-AppVeyor-Environment-Variables","source":null,"target":null}},{"data":{"id":"Show-Info","source":null,"target":null}},{"data":{"id":"Create-NuGet-Packages","source":null,"target":null}},{"data":{"id":"31acfc2c-cdb5-4855-b0b6-143aab7a8100","source":"Create-NuGet-Packages","target":"Clean"}},{"data":{"id":"1092f343-a833-4b81-bffc-9990540139b9","source":"Create-NuGet-Packages","target":"DotNetCore-Build"}},{"data":{"id":"DotNetCore-Build","source":null,"target":null}},{"data":{"id":"43691e72-80bb-4486-b2c2-552b1a014bca","source":"DotNetCore-Build","target":"Clean"}},{"data":{"id":"a9c186df-521b-4e2a-96a4-15eac02590b5","source":"DotNetCore-Build","target":"DotNetCore-Restore"}},{"data":{"id":"DotNetCore-Restore","source":null,"target":null}},{"data":{"id":"Clean","source":null,"target":null}},{"data":{"id":"345ef766-762f-4818-9085-81a4a58d6e0c","source":"Clean","target":"Show-Info"}},{"data":{"id":"bec3f76f-95a3-4254-9a85-081c55184aea","source":"Clean","target":"Print-AppVeyor-Environment-Variables"}},{"data":{"id":"Print-AppVeyor-Environment-Variables","source":null,"target":null}},{"data":{"id":"Show-Info","source":null,"target":null}},{"data":{"id":"Clean","source":null,"target":null}},{"data":{"id":"b7229ab2-a007-4707-9474-127a33a42ec0","source":"Clean","target":"Show-Info"}},{"data":{"id":"ade5fad4-c7f1-42ce-8f19-82540a9dadd1","source":"Clean","target":"Print-AppVeyor-Environment-Variables"}},{"data":{"id":"Print-AppVeyor-Environment-Variables","source":null,"target":null}},{"data":{"id":"Show-Info","source":null,"target":null}},{"data":{"id":"Test","source":null,"target":null}},{"data":{"id":"d6297c57-e5f5-4de2-b0cc-615e87d81178","source":"Test","target":"DotNetCore-Build"}},{"data":{"id":"8d4bd93b-08ec-4525-9375-ac34e3856fae","source":"Test","target":"DotNetCore-Test"}},{"data":{"id":"DotNetCore-Test","source":null,"target":null}},{"data":{"id":"3a3274ba-6738-494f-a479-6abfaf7a0014","source":"DotNetCore-Test","target":"Install-OpenCover"}},{"data":{"id":"Install-OpenCover","source":null,"target":null}},{"data":{"id":"e1a73973-3b6b-46b5-af12-7e62b34183d3","source":"Install-OpenCover","target":"Install-ReportGenerator"}},{"data":{"id":"Install-ReportGenerator","source":null,"target":null}},{"data":{"id":"2f4a8ffb-6243-4ca2-bf89-855c71aab62d","source":"Install-ReportGenerator","target":"DotNetCore-Build"}},{"data":{"id":"DotNetCore-Build","source":null,"target":null}},{"data":{"id":"f72113a8-4a40-49ce-8d72-cd0a81736324","source":"DotNetCore-Build","target":"Clean"}},{"data":{"id":"eb3838e7-90ca-474a-b870-8b9e0ac2ad57","source":"DotNetCore-Build","target":"DotNetCore-Restore"}},{"data":{"id":"DotNetCore-Restore","source":null,"target":null}},{"data":{"id":"Clean","source":null,"target":null}},{"data":{"id":"a683570f-390d-4f9f-8b62-e95251795d68","source":"Clean","target":"Show-Info"}},{"data":{"id":"3c31b287-c173-4985-84b6-46b1ca2b561f","source":"Clean","target":"Print-AppVeyor-Environment-Variables"}},{"data":{"id":"Print-AppVeyor-Environment-Variables","source":null,"target":null}},{"data":{"id":"Show-Info","source":null,"target":null}},{"data":{"id":"DotNetCore-Build","source":null,"target":null}},{"data":{"id":"114b0937-5c06-4365-a1d2-e9d047c317de","source":"DotNetCore-Build","target":"Clean"}},{"data":{"id":"12dc23dd-47bb-48fb-b4f0-5eb3bb3a08e2","source":"DotNetCore-Build","target":"DotNetCore-Restore"}},{"data":{"id":"DotNetCore-Restore","source":null,"target":null}},{"data":{"id":"Clean","source":null,"target":null}},{"data":{"id":"9448d748-66eb-420c-adbb-48980805dfde","source":"Clean","target":"Show-Info"}},{"data":{"id":"958d6605-338e-404c-a2b3-c61c0ec7311a","source":"Clean","target":"Print-AppVeyor-Environment-Variables"}},{"data":{"id":"Print-AppVeyor-Environment-Variables","source":null,"target":null}},{"data":{"id":"Show-Info","source":null,"target":null}},{"data":{"id":"Analyze","source":null,"target":null}},{"data":{"id":"5652682a-f232-4aab-a896-49a024bacd6d","source":"Analyze","target":"DupFinder"}},{"data":{"id":"3015c3e2-a0df-4fa5-9acc-b5853a387016","source":"Analyze","target":"InspectCode"}},{"data":{"id":"InspectCode","source":null,"target":null}},{"data":{"id":"1ebbef6e-9eaa-41c6-ae19-8de6d05e32fd","source":"InspectCode","target":"DotNetCore-Build"}},{"data":{"id":"DotNetCore-Build","source":null,"target":null}},{"data":{"id":"c92390a2-f65b-431c-8aa2-0993a4eccdf1","source":"DotNetCore-Build","target":"Clean"}},{"data":{"id":"2106dbd9-27c8-4a1e-8bd7-8e94c151c763","source":"DotNetCore-Build","target":"DotNetCore-Restore"}},{"data":{"id":"DotNetCore-Restore","source":null,"target":null}},{"data":{"id":"Clean","source":null,"target":null}},{"data":{"id":"6313d227-13d6-4719-8141-603874ad4609","source":"Clean","target":"Show-Info"}},{"data":{"id":"0a5a6353-d067-4a88-aafd-164261d59b08","source":"Clean","target":"Print-AppVeyor-Environment-Variables"}},{"data":{"id":"Print-AppVeyor-Environment-Variables","source":null,"target":null}},{"data":{"id":"Show-Info","source":null,"target":null}},{"data":{"id":"DupFinder","source":null,"target":null}},{"data":{"id":"ed7b4017-296c-48e7-b0ed-15ca3da93d79","source":"DupFinder","target":"DotNetCore-Build"}},{"data":{"id":"DotNetCore-Build","source":null,"target":null}},{"data":{"id":"d0b60664-dbbe-4e48-8433-410a1cd45a06","source":"DotNetCore-Build","target":"Clean"}},{"data":{"id":"4b40e176-a61f-49d2-a3b4-395c3ff5a8bb","source":"DotNetCore-Build","target":"DotNetCore-Restore"}},{"data":{"id":"DotNetCore-Restore","source":null,"target":null}},{"data":{"id":"Clean","source":null,"target":null}},{"data":{"id":"26b468e0-2ca6-4f28-9195-7e935de147df","source":"Clean","target":"Show-Info"}},{"data":{"id":"6f519118-eedf-45e9-9434-2236ae6cafca","source":"Clean","target":"Print-AppVeyor-Environment-Variables"}},{"data":{"id":"Print-AppVeyor-Environment-Variables","source":null,"target":null}},{"data":{"id":"Show-Info","source":null,"target":null}},{"data":{"id":"Export-Release-Notes","source":null,"target":null}}]